tulip.py
pytulip-0.2.3.dist-info/LICENSE
pytulip-0.2.3.dist-info/METADATA
pytulip-0.2.3.dist-info/WHEEL
pytulip-0.2.3.dist-info/entry_points.txt
pytulip-0.2.3.dist-info/top_level.txt
pytulip-0.2.3.dist-info/RECORD
